mcp_layer/__init__.py
mcp_layer/configuration.py
mcp_layer/schemas.py
mcp_layer/service.py
mcp_layer/mcp_server/__init__.py
mcp_layer/mcp_server/llama_server.py
mcp_layer/mcp_server/math_server.py
mcp_layer/similarity_search/__init__.py
mcp_layer/similarity_search/configuration.py
mcp_layer/similarity_search/repository_faiss.py
mcp_layer-0.1.0.dist-info/METADATA
mcp_layer-0.1.0.dist-info/WHEEL
mcp_layer-0.1.0.dist-info/entry_points.txt
mcp_layer-0.1.0.dist-info/RECORD
